{
  "date": "2026-07-11",
  "posts": [
    {
      "img_class": "blog-card__img--1",
      "langs": {
        "en": {
          "slug": "surah-al-mulk-spiritual-benefits",
          "title": "Surah Al-Mulk: Spiritual Benefits and the Sunnah of Nightly Recitation",
          "meta_desc": "The spiritual benefits of Surah Al-Mulk (Chapter 67): its role as an intercessor, the hadith on protection from the punishment of the grave, key themes, and how to make it a nightly habit.",
          "og_title": "Surah Al-Mulk: Benefits, Meaning & the Nightly Sunnah",
          "og_desc": "Why the Prophet ﷺ recited Surah Al-Mulk every night: the hadith on intercession, the key themes of this 30-verse surah, and how to build the habit.",
          "category": "Quran",
          "h1": "Surah Al-Mulk: Spiritual Benefits and the Sunnah of Nightly Recitation",
          "read_label": "7 min read",
          "excerpt": "Surah Al-Mulk — Chapter 67 of the Quran — is known as the Intercessor. The Prophet ﷺ recited it every night without exception. Explore its key themes, the hadith on its reward, and how to make it part of your routine.",
          "sections": [
            {
              "t": "p",
              "html": "<strong>Surah Al-Mulk</strong> (The Sovereignty) is the 67th chapter of the Quran, revealed in Makkah, comprising 30 verses. Among all the chapters of the Quran, it holds a uniquely honoured position: the Prophet ﷺ singled it out as one he would never sleep without reciting, and described it as a surah that intercedes for its companion in the grave. Understanding what this surah actually says — and what it invites us to reflect on — is the first step to making it a living part of daily worship."
            },
            {
              "t": "h2",
              "text": "The Opening Declaration: All Dominion Belongs to Allah"
            },
            {
              "t": "quran",
              "text": "تَبَارَكَ الَّذِي بِيَدِهِ الْمُلْكُ وَهُوَ عَلَى كُلِّ شَيْءٍ قَدِيرٌ ۝ الَّذِي خَلَقَ الْمَوْتَ وَالْحَيَاةَ لِيَبْلُوَكُمْ أَيُّكُمْ أَحْسَنُ عَمَلًا ۚ وَهُوَ الْعَزِيزُ الْغَفُورُ",
              "ref": "Surah Al-Mulk, 67:1–2"
            },
            {
              "t": "p",
              "html": "\"Blessed is He in Whose Hand is all dominion, and He is over all things competent — He who created death and life to test you as to which of you is best in deed. And He is the Exalted in Might, the Forgiving.\" The surah opens not by mentioning a ritual, but by anchoring the believer in a cosmic truth: <em>all power belongs to Allah alone</em>. The Arabic word <em>tabarak</em> — from which the surah takes its beloved alternative name <strong>Al-Tabarak</strong> — describes a source of perpetual, overflowing blessing. Returning to this declaration every night before sleep recalibrates the heart."
            },
            {
              "t": "h2",
              "text": "The Hadith: A Surah of Thirty Verses That Intercedes"
            },
            {
              "t": "p",
              "html": "Abu Hurairah (RA) narrated that the Prophet ﷺ said: <em>\"There is a surah in the Quran of thirty verses that will intercede for a man until he is forgiven — it is: Tabarak alladhi biyadihi al-mulk.\"</em> (Abu Dawud 1400; Tirmidhi 2891, graded hasan; Ibn Majah 3786) Scholars explain that this intercession is directed toward protecting its reciter from the punishment of the grave. For this reason early scholars gave the surah additional titles: <strong>Al-Mani'ah</strong> (the one that prevents the punishment) and <strong>Al-Waqiyah</strong> (the protective shield)."
            },
            {
              "t": "h2",
              "text": "The Nightly Sunnah of the Prophet ﷺ"
            },
            {
              "t": "p",
              "html": "Jabir ibn Abdullah (RA) narrated that the Prophet ﷺ would not sleep until he had recited Surah As-Sajdah (32) and Surah Al-Mulk (67). (Tirmidhi 2892, graded hasan) This established a nightly practice that the Companions and their successors preserved. Many scholars recommend pairing the recitation with a broader night-time routine; for the full prophetic etiquette of sleeping, see our guide to the <a href='sunnah-of-sleeping.html'>sunnah of sleeping</a>."
            },
            {
              "t": "h2",
              "text": "Key Themes of Surah Al-Mulk"
            },
            {
              "t": "cards",
              "cards": [
                {
                  "icon": "🌌",
                  "title": "Allah's Absolute Sovereignty",
                  "text": "All dominion and power belong to Allah alone. Returning to this truth each night builds a heart at rest, regardless of worldly anxieties."
                },
                {
                  "icon": "⚖️",
                  "title": "Life and Death as a Test",
                  "text": "Verse 2 reveals that death and life were created to test which of us is best in deed — not most in deed. Sincerity and quality matter more than quantity."
                },
                {
                  "icon": "🔭",
                  "title": "The Heavens: Look for a Flaw",
                  "text": "Verses 3–5 describe the seven heavens in perfect layers, adorned with stars, without any crack or gap. Allah challenges us to look — and find none."
                },
                {
                  "icon": "💧",
                  "title": "Provision Comes Only from Allah",
                  "text": "The surah closes by asking: if the water beneath the earth disappeared, who could bring forth flowing water? The answer is Allah alone — a call to total reliance on Him."
                }
              ]
            },
            {
              "t": "h2",
              "text": "A Verse to Carry Through the Day"
            },
            {
              "t": "quran",
              "text": "أَلَا يَعْلَمُ مَنْ خَلَقَ وَهُوَ اللَّطِيفُ الْخَبِيرُ",
              "ref": "Surah Al-Mulk, 67:14"
            },
            {
              "t": "p",
              "html": "\"Does He who created not know — while He is the Subtle, the Acquainted?\" This verse stands as one of the Quran's most direct responses to anxiety about the unseen. Allah created you in full knowledge of your nature, your situation, and your needs. When we combine it with the opening message of sovereign power, the believer gains a complete frame: <em>Allah is in control, and He knows you perfectly</em>."
            },
            {
              "t": "h2",
              "text": "Building the Nightly Habit"
            },
            {
              "t": "p",
              "html": "The most reliable way to make Surah Al-Mulk a nightly constant is to attach it to an existing habit: reciting it after Isha prayer, or as you turn off the lights. Begin with a few verses at a time, reading alongside the translation to absorb the meaning, and gradually build toward reciting all 30 from memory. The <a href='virtue-of-learning-and-teaching-quran.html'>virtue of learning and teaching the Quran</a> is immense, and at 30 verses this surah is an excellent place to begin."
            }
          ],
          "cta": {
            "title": "Recite Surah Al-Mulk Every Night with DeenPal",
            "text": "Get the full Arabic text of Surah Al-Mulk with transliteration, audio and translation — plus a nightly reminder — in one free app.",
            "btn": "Download DeenPal Free"
          },
          "footer_nav": {
            "prev": {
              "href": "surah-al-ikhlas-meaning-virtues.html",
              "title": "Surah Al-Ikhlas: Meaning and Virtues"
            },
            "related": {
              "href": "surah-ya-sin-meaning-virtues.html",
              "title": "Surah Ya-Sin: Meaning, Virtues and When to Recite It"
            }
          },
          "faq": [
            {
              "q": "What is the main benefit of reading Surah Al-Mulk every night?",
              "a": "The Prophet ﷺ said that a surah of 30 verses — Surah Al-Mulk — will intercede for its reciter until they are forgiven, and scholars relate this specifically to protection from the punishment of the grave. (Abu Dawud, Tirmidhi, Ibn Majah)"
            },
            {
              "q": "What are the other names of Surah Al-Mulk?",
              "a": "Surah Al-Mulk is also known as Al-Tabarak (after its opening word), Al-Mani'ah (the Preventer of punishment), and Al-Waqiyah (the Protective Shield). These names reflect its role as an intercessor."
            },
            {
              "q": "Did the Prophet ﷺ recite Surah Al-Mulk every night?",
              "a": "Yes. Jabir ibn Abdullah (RA) narrated that the Prophet ﷺ would not sleep until he had recited Surah As-Sajdah and Surah Al-Mulk. This is narrated in Tirmidhi and graded hasan."
            },
            {
              "q": "How many verses does Surah Al-Mulk have and how long does it take to recite?",
              "a": "Surah Al-Mulk has 30 verses. At a measured, unhurried pace it takes approximately four to six minutes to recite in full."
            },
            {
              "q": "What is the main theme of Surah Al-Mulk?",
              "a": "The surah establishes Allah's absolute sovereignty, explains that life and death are a test to see who does the best deed, and reminds us that all provision and power belong to Allah alone."
            },
            {
              "q": "When is the best time to recite Surah Al-Mulk?",
              "a": "The prophetic practice was to recite it at night before sleeping. Many Muslims recite it after Isha prayer or just before bed, following the established sunnah."
            }
          ]
        },
        "nl": {
          "slug": "soera-al-mulk-spirituele-voordelen",
          "title": "Soera Al-Mulk: Spirituele Voordelen en de Nachtelijke Soenna",
          "meta_desc": "De spirituele voordelen van Soera Al-Mulk (hoofdstuk 67): haar rol als voorspreekster, de hadith over bescherming tegen de kwelling van het graf, kernthema's en hoe je het een nachtgewoonte maakt.",
          "og_title": "Soera Al-Mulk: Voordelen, Betekenis en de Nachtelijke Soenna",
          "og_desc": "Waarom de Profeet ﷺ Soera Al-Mulk elke nacht reciteerde: de hadith over voorspraak, de kernthema's en hoe je deze 30 verzen in je routine opneemt.",
          "category": "Koran",
          "h1": "Soera Al-Mulk: Spirituele Voordelen en de Nachtelijke Soenna",
          "read_label": "7 min lezen",
          "excerpt": "Soera Al-Mulk — hoofdstuk 67 van de Koran — staat bekend als de Voorspreekster. De Profeet ﷺ reciteerde het elke nacht. Ontdek de kernthema's, de hadith over de beloning en hoe je het in je routine opneemt.",
          "sections": [
            {
              "t": "p",
              "html": "<strong>Soera Al-Mulk</strong> (De Heerschappij) is het 67e hoofdstuk van de Koran, geopenbaard in Mekka, en telt 30 verzen. Onder alle soera's van de Koran neemt het een bijzonder geëerde plaats in: de Profeet ﷺ reciteerde het elke avond voor het slapen gaan en beschreef het als een soera die voor haar metgezel voorspraak doet in het graf. Begrijpen wat deze soera zegt en waartoe zij ons uitnodigt te overdenken, is de eerste stap om haar een levend deel van de dagelijkse aanbidding te maken."
            },
            {
              "t": "h2",
              "text": "De Openingsverklaring: Alle Heerschappij Behoort aan Allah"
            },
            {
              "t": "quran",
              "text": "تَبَارَكَ الَّذِي بِيَدِهِ الْمُلْكُ وَهُوَ عَلَى كُلِّ شَيْءٍ قَدِيرٌ ۝ الَّذِي خَلَقَ الْمَوْتَ وَالْحَيَاةَ لِيَبْلُوَكُمْ أَيُّكُمْ أَحْسَنُ عَمَلًا ۚ وَهُوَ الْعَزِيزُ الْغَفُورُ",
              "ref": "Soera Al-Mulk, 67:1–2"
            },
            {
              "t": "p",
              "html": "\"Gezegend is Degene in Wiens Hand de heerschappij is, en Hij is over alle dingen Machtig — Die de dood en het leven schiep om jullie te beproeven: wie van jullie het beste in daden is. En Hij is de Almachtige, de Vergevensgezinde.\" De soera opent niet met een ritueel, maar verankert de gelovige in een kosmische waarheid: <em>alle macht behoort aan Allah alleen</em>. Het Arabische woord <em>tabarak</em> — waarvan de soera de geliefde bijnaam <strong>Al-Tabarak</strong> ontleent — beschrijft een bron van voortdurende, overvloeiende zegen. Elke nacht naar deze verklaring terugkeren herstelt de rust in het hart."
            },
            {
              "t": "h2",
              "text": "De Hadith: Een Soera van Dertig Verzen die Voorspraak Doet"
            },
            {
              "t": "p",
              "html": "Abu Hurairah (ra) overleverde dat de Profeet ﷺ zei: <em>\"Er is een soera in de Koran van dertig verzen die voor een man zal voorspreken totdat hij vergeven wordt — het is: Tabarak alladhi biyadihi al-mulk.\"</em> (Abu Dawud 1400; Tirmidhi 2891, geclassificeerd als hasan; Ibn Majah 3786) Geleerden leggen uit dat deze voorspraak specifiek gericht is op het beschermen van de recitant tegen de kwelling van het graf. Vroege geleerden gaven de soera daarom de titels <strong>Al-Mani'ah</strong> (de Voorkomstige van de straf) en <strong>Al-Waqiyah</strong> (het Beschermende Schild)."
            },
            {
              "t": "h2",
              "text": "De Nachtelijke Soenna van de Profeet ﷺ"
            },
            {
              "t": "p",
              "html": "Jabir ibn Abdullah (ra) overleverde dat de Profeet ﷺ niet sliep voordat hij Soera As-Sajdah (32) en Soera Al-Mulk (67) had gereciteerd. (Tirmidhi 2892, hasan) Dit vestigde een nachtelijk gebruik dat de metgezellen en hun opvolgers bewaarden. Veel geleerden bevelen aan de recitatie te combineren met een bredere avondroutine; zie onze gids over de <a href='sunnah-van-slapen.html'>soenna van het slapen</a>."
            },
            {
              "t": "h2",
              "text": "Kernthema's van Soera Al-Mulk"
            },
            {
              "t": "cards",
              "cards": [
                {
                  "icon": "🌌",
                  "title": "Allah's Absolute Heerschappij",
                  "text": "Alle heerschappij en macht behoren aan Allah alleen. Elke nacht naar deze waarheid terugkeren bouwt een hart op dat rust vindt, ongeacht wereldse zorgen."
                },
                {
                  "icon": "⚖️",
                  "title": "Leven en Dood als Beproeving",
                  "text": "Vers 2 onthult dat dood en leven geschapen zijn om te beproeven wie van ons het beste in daden is — niet het meeste. Oprechtheid en kwaliteit tellen meer dan kwantiteit."
                },
                {
                  "icon": "🔭",
                  "title": "De Hemelen: Zoek een Gebrek",
                  "text": "Verzen 3–5 beschrijven de zeven hemelen in perfecte lagen, versierd met sterren, zonder enige barst of gebrek. Allah daagt ons uit om te kijken — en niets te vinden."
                },
                {
                  "icon": "💧",
                  "title": "Voorziening Komt Alleen van Allah",
                  "text": "De soera sluit af met de vraag: als het water onder de aarde zou verdwijnen, wie zou dan stromend water kunnen brengen? Alleen Allah — een oproep tot volledige afhankelijkheid van Hem."
                }
              ]
            },
            {
              "t": "h2",
              "text": "Een Vers om bij te Dragen"
            },
            {
              "t": "quran",
              "text": "أَلَا يَعْلَمُ مَنْ خَلَقَ وَهُوَ اللَّطِيفُ الْخَبِيرُ",
              "ref": "Soera Al-Mulk, 67:14"
            },
            {
              "t": "p",
              "html": "\"Weet Hij Die schiep dan niet — terwijl Hij de Subtiele, de Alwetende is?\" Dit vers is een van de krachtigste antwoorden van de Koran op angst voor het onbekende. Allah schiep jou met volledige kennis van je aard, je situatie en je behoeften. Gecombineerd met de openingsboodschap van soevereine macht geeft vers 67:14 de gelovige een compleet kader: <em>Allah is in controle en kent jou volledig</em>."
            },
            {
              "t": "h2",
              "text": "De Nachtelijke Gewoonte Opbouwen"
            },
            {
              "t": "p",
              "html": "De betrouwbaarste manier om Soera Al-Mulk elke nacht te reciteren, is het koppelen aan een bestaande gewoonte: na het Isha-gebed of wanneer je het licht uitzet. Begin met een paar verzen tegelijk, lees mee met de vertaling om de betekenis op te nemen, en bouw geleidelijk op naar het uit het hoofd reciteren van alle 30 verzen. De <a href='deugd-van-leren-en-onderwijzen-koran.html'>deugd van het leren en onderwijzen van de Koran</a> is enorm, en met 30 verzen is deze soera een uitstekende plek om te beginnen."
            }
          ],
          "cta": {
            "title": "Reciteer Soera Al-Mulk Elke Nacht met DeenPal",
            "text": "Krijg de volledige Arabische tekst van Soera Al-Mulk met transliteratie, audio en vertaling — plus een nachtelijke herinnering — in één gratis app.",
            "btn": "Download DeenPal Gratis"
          },
          "footer_nav": {
            "prev": {
              "href": "soera-al-ikhlas-betekenis-deugden.html",
              "title": "Soera Al-Ikhlas: Betekenis en Deugden"
            },
            "related": {
              "href": "surah-ya-sin-betekenis-deugden.html",
              "title": "Soera Ya-Sin: Betekenis, Deugden en Wanneer te Reciteren"
            }
          },
          "faq": [
            {
              "q": "Wat is het belangrijkste voordeel van het lezen van Soera Al-Mulk elke nacht?",
              "a": "De Profeet ﷺ zei dat een soera van 30 verzen — Soera Al-Mulk — voor haar recitant voorspraak doet totdat hij vergeven wordt, en geleerden relateren dit specifiek aan bescherming tegen de kwelling van het graf. (Abu Dawud, Tirmidhi, Ibn Majah)"
            },
            {
              "q": "Wat zijn de andere namen van Soera Al-Mulk?",
              "a": "Soera Al-Mulk staat ook bekend als Al-Tabarak (naar het openingswoord), Al-Mani'ah (de Voorkomstige van de straf) en Al-Waqiyah (het Beschermende Schild)."
            },
            {
              "q": "Reciteerde de Profeet ﷺ Soera Al-Mulk werkelijk elke nacht?",
              "a": "Ja. Jabir ibn Abdullah (ra) overleverde dat de Profeet ﷺ niet sliep voordat hij Soera As-Sajdah en Soera Al-Mulk had gereciteerd. Dit is overgeleverd in Tirmidhi en geclassificeerd als hasan."
            },
            {
              "q": "Hoeveel verzen heeft Soera Al-Mulk en hoe lang duurt het reciteren?",
              "a": "Soera Al-Mulk heeft 30 verzen. Op een rustig tempo duurt het reciteren circa vier tot zes minuten."
            },
            {
              "q": "Wat is het kernthema van Soera Al-Mulk?",
              "a": "De soera vestigt Allah's absolute heerschappij, legt uit dat leven en dood een beproeving zijn om te zien wie de beste daden verricht, en herinnert ons eraan dat alle voorziening en macht aan Allah alleen toebehoren."
            },
            {
              "q": "Wanneer is de beste tijd om Soera Al-Mulk te reciteren?",
              "a": "De profetische praktijk was om het 's nachts voor het slapen te reciteren. Veel moslims reciteren het na het Isha-gebed of vlak voor het slapengaan."
            }
          ]
        },
        "de": {
          "slug": "sure-al-mulk-spirituelle-vorteile",
          "title": "Sure Al-Mulk: Spirituelle Vorteile und die nächtliche Sunna",
          "meta_desc": "Die spirituellen Vorteile von Sure Al-Mulk (Kapitel 67): ihre Rolle als Fürsprecherin, der Hadith über Schutz vor der Grabstrafe, Kernthemen und wie man sie zur nächtlichen Gewohnheit macht.",
          "og_title": "Sure Al-Mulk: Vorteile, Bedeutung und die nächtliche Sunna",
          "og_desc": "Warum der Prophet ﷺ Sure Al-Mulk jede Nacht rezitierte: der Hadith über die Fürsprache, die Kernthemen dieser 30-Verse-Sure und Tipps zum Auswendiglernen.",
          "category": "Quran",
          "h1": "Sure Al-Mulk: Spirituelle Vorteile und die nächtliche Sunna",
          "read_label": "7 Min. Lesezeit",
          "excerpt": "Sure Al-Mulk — Kapitel 67 des Qurans — ist als die Fürsprecherin bekannt. Der Prophet ﷺ rezitierte sie jede Nacht. Entdecke ihre Kernthemen, den Hadith über ihre Belohnung und wie du sie in deinen Alltag einbaust.",
          "sections": [
            {
              "t": "p",
              "html": "<strong>Sure Al-Mulk</strong> (Die Herrschaft) ist das 67. Kapitel des Qurans, in Mekka offenbart, und umfasst 30 Verse. Unter allen Suren des Qurans nimmt sie eine besonders geehrte Stellung ein: Der Prophet ﷺ schlief nie, ohne sie rezitiert zu haben, und beschrieb sie als eine Sure, die für ihren Begleiter im Grab Fürsprache einlegt. Zu verstehen, was diese Sure sagt — und wozu sie uns einlädt zu bedenken — ist der erste Schritt, um sie zu einem lebendigen Teil der täglichen Anbetung zu machen."
            },
            {
              "t": "h2",
              "text": "Die Eröffnungserklärung: Alle Herrschaft gehört Allah"
            },
            {
              "t": "quran",
              "text": "تَبَارَكَ الَّذِي بِيَدِهِ الْمُلْكُ وَهُوَ عَلَى كُلِّ شَيْءٍ قَدِيرٌ ۝ الَّذِي خَلَقَ الْمَوْتَ وَالْحَيَاةَ لِيَبْلُوَكُمْ أَيُّكُمْ أَحْسَنُ عَمَلًا ۚ وَهُوَ الْعَزِيزُ الْغَفُورُ",
              "ref": "Sure Al-Mulk, 67:1–2"
            },
            {
              "t": "p",
              "html": "„Gepriesen sei Er, in Dessen Hand die Herrschaft liegt, und Er ist über alle Dinge Allmächtig — Der den Tod und das Leben erschuf, um euch zu prüfen, wer von euch am besten in Taten ist. Und Er ist der Erhabene, der Vergebende.\" Die Sure beginnt nicht mit einem Ritual, sondern verankert den Gläubigen in einer kosmischen Wahrheit: <em>Alle Macht gehört Allah allein</em>. Das arabische Wort <em>tabarak</em> — dem die Sure ihren geliebten Beinamen <strong>Al-Tabarak</strong> verdankt — beschreibt eine Quelle beständigen, überfließenden Segens. Jede Nacht zu dieser Erklärung zurückzukehren, stellt das Herz neu aus."
            },
            {
              "t": "h2",
              "text": "Der Hadith: Eine Sure von dreißig Versen, die Fürsprache einlegt"
            },
            {
              "t": "p",
              "html": "Abu Hurairah (ra) überlieferte, dass der Prophet ﷺ sagte: <em>„Es gibt eine Sure im Quran mit dreißig Versen, die für einen Mann Fürsprache einlegen wird, bis er vergeben wird — sie lautet: Tabarak alladhi biyadihi al-mulk.\"</em> (Abu Dawud 1400; Tirmidhi 2891, als hasan eingestuft; Ibn Majah 3786) Gelehrte erklären, dass sich diese Fürsprache speziell auf den Schutz des Lesers vor der Grabstrafe bezieht. Frühe Gelehrte gaben der Sure daher die Titel <strong>Al-Mani'ah</strong> (die Verhüterin der Strafe) und <strong>Al-Waqiyah</strong> (das schützende Schild)."
            },
            {
              "t": "h2",
              "text": "Die nächtliche Sunna des Propheten ﷺ"
            },
            {
              "t": "p",
              "html": "Jabir ibn Abdullah (ra) überlieferte, dass der Prophet ﷺ nicht schlief, bis er Sure As-Sajdah (32) und Sure Al-Mulk (67) rezitiert hatte. (Tirmidhi 2892, hasan) Dies begründete eine nächtliche Praxis, die die Gefährten und ihre Nachfolger bewahrten. Viele Gelehrte empfehlen, die Rezitation in eine umfassendere Abendroutine einzubetten; für die vollständige prophetische Schlafetikette, siehe unsere Anleitung zur <a href='sunna-des-schlafens.html'>Sunna des Schlafens</a>."
            },
            {
              "t": "h2",
              "text": "Kernthemen von Sure Al-Mulk"
            },
            {
              "t": "cards",
              "cards": [
                {
                  "icon": "🌌",
                  "title": "Allahs absolute Herrschaft",
                  "text": "Alle Herrschaft und Macht gehören Allah allein. Jede Nacht zu dieser Wahrheit zurückzukehren, formt ein Herz, das Ruhe findet, ungeachtet weltlicher Sorgen."
                },
                {
                  "icon": "⚖️",
                  "title": "Leben und Tod als Prüfung",
                  "text": "Vers 2 enthüllt, dass Tod und Leben erschaffen wurden, um zu prüfen, wer von uns am besten in Taten ist — nicht am meisten. Aufrichtigkeit und Qualität zählen mehr als Quantität."
                },
                {
                  "icon": "🔭",
                  "title": "Die Himmel: Suche nach einem Makel",
                  "text": "Verse 3–5 beschreiben die sieben Himmel in perfekten Schichten, mit Sternen geschmückt, ohne Riss oder Spalt. Allah fordert uns auf: Schaut — und findet keinen."
                },
                {
                  "icon": "💧",
                  "title": "Versorgung kommt allein von Allah",
                  "text": "Die Sure schließt mit der Frage: Wenn das Wasser unter der Erde verschwände, wer könnte fließendes Wasser herbeibringen? Nur Allah — eine Mahnung zur völligen Abhängigkeit von Ihm."
                }
              ]
            },
            {
              "t": "h2",
              "text": "Ein Vers zum Mitnehmen"
            },
            {
              "t": "quran",
              "text": "أَلَا يَعْلَمُ مَنْ خَلَقَ وَهُوَ اللَّطِيفُ الْخَبِيرُ",
              "ref": "Sure Al-Mulk, 67:14"
            },
            {
              "t": "p",
              "html": "„Weiß Er, Der schuf, denn nicht — während Er der Subtile, der Allkundige ist?\" Dieser Vers ist eine der kraftvollsten Antworten des Qurans auf Sorge um das Unbekannte. Allah erschuf dich mit vollständigem Wissen um deine Natur, deine Lage und deine Bedürfnisse. Verbunden mit der Eröffnungsbotschaft souveräner Macht gibt Vers 67:14 dem Gläubigen einen vollständigen Rahmen: <em>Allah hat die Kontrolle und kennt dich vollkommen</em>."
            },
            {
              "t": "h2",
              "text": "Die nächtliche Gewohnheit aufbauen"
            },
            {
              "t": "p",
              "html": "Der zuverlässigste Weg, Sure Al-Mulk zur nächtlichen Konstante zu machen, ist es, sie an eine bestehende Gewohnheit zu koppeln: nach dem Isha-Gebet oder wenn du das Licht ausmachst. Beginne mit wenigen Versen, lies sie neben der Übersetzung, um den Sinn aufzunehmen, und steigere dich schrittweise bis zur auswendigen Rezitation aller 30 Verse. Die <a href='tugend-des-lernens-und-lehrens-des-qurans.html'>Tugend des Lernens und Lehrens des Qurans</a> ist immens, und mit 30 Versen ist diese Sure ein ausgezeichneter Ausgangspunkt."
            }
          ],
          "cta": {
            "title": "Rezitiere Sure Al-Mulk jede Nacht mit DeenPal",
            "text": "Erhalte den vollständigen arabischen Text von Sure Al-Mulk mit Transliteration, Audio und Übersetzung — plus eine nächtliche Erinnerung — in einer kostenlosen App.",
            "btn": "DeenPal kostenlos laden"
          },
          "footer_nav": {
            "prev": {
              "href": "sure-al-ikhlas-bedeutung-vorzuge.html",
              "title": "Sure Al-Ikhlas: Bedeutung und Vorzüge"
            },
            "related": {
              "href": "sure-ya-sin-bedeutung-vorzuge.html",
              "title": "Sure Ya-Sin: Bedeutung, Vorzüge und wann man sie rezitiert"
            }
          },
          "faq": [
            {
              "q": "Was ist der hauptsächliche Nutzen des täglichen Rezitierens von Sure Al-Mulk?",
              "a": "Der Prophet ﷺ sagte, eine Sure mit 30 Versen — Sure Al-Mulk — werde für ihren Leser Fürsprache einlegen, bis er vergeben wird. Gelehrte beziehen dies speziell auf den Schutz vor der Grabstrafe. (Abu Dawud, Tirmidhi, Ibn Majah)"
            },
            {
              "q": "Welche anderen Namen hat Sure Al-Mulk?",
              "a": "Sure Al-Mulk ist auch bekannt als Al-Tabarak (nach dem Eröffnungswort), Al-Mani'ah (die Verhüterin der Strafe) und Al-Waqiyah (das schützende Schild)."
            },
            {
              "q": "Hat der Prophet ﷺ Sure Al-Mulk wirklich jede Nacht rezitiert?",
              "a": "Ja. Jabir ibn Abdullah (ra) überlieferte, dass der Prophet ﷺ nicht schlief, bis er Sure As-Sajdah und Sure Al-Mulk rezitiert hatte. Dies ist bei Tirmidhi überliefert und als hasan eingestuft."
            },
            {
              "q": "Wie viele Verse hat Sure Al-Mulk und wie lange dauert das Rezitieren?",
              "a": "Sure Al-Mulk hat 30 Verse. In einem gemächlichen Tempo dauert die Rezitation etwa vier bis sechs Minuten."
            },
            {
              "q": "Was ist das Kernthema von Sure Al-Mulk?",
              "a": "Die Sure stellt Allahs absolute Herrschaft fest, erklärt, dass Leben und Tod eine Prüfung sind, wer die besten Taten vollbringt, und erinnert daran, dass alle Versorgung und Macht allein Allah gehören."
            },
            {
              "q": "Wann ist die beste Zeit, Sure Al-Mulk zu rezitieren?",
              "a": "Die prophetische Praxis war es, sie nachts vor dem Schlafen zu rezitieren. Viele Muslime rezitieren sie nach dem Isha-Gebet oder kurz vor dem Schlafengehen."
            }
          ]
        },
        "fr": {
          "slug": "sourate-al-mulk-bienfaits-spirituels",
          "title": "Sourate Al-Mulk : bienfaits spirituels et la sunna de la récitation nocturne",
          "meta_desc": "Les bienfaits spirituels de la Sourate Al-Mulk (chapitre 67) : son rôle d'intercesseur, le hadith sur la protection contre le châtiment de la tombe, les thèmes clés et comment en faire une habitude nocturne.",
          "og_title": "Sourate Al-Mulk : bienfaits, signification et sunna nocturne",
          "og_desc": "Pourquoi le Prophète ﷺ récitait la Sourate Al-Mulk chaque nuit : le hadith sur l'intercession, les thèmes clés de cette sourate de 30 versets et comment bâtir l'habitude.",
          "category": "Coran",
          "h1": "Sourate Al-Mulk : bienfaits spirituels et la sunna de la récitation nocturne",
          "read_label": "7 min de lecture",
          "excerpt": "La Sourate Al-Mulk — chapitre 67 du Coran — est connue comme l'Intercesseur. Le Prophète ﷺ la récitait chaque nuit. Découvrez ses thèmes clés, le hadith sur sa récompense et comment l'intégrer à votre routine.",
          "sections": [
            {
              "t": "p",
              "html": "<strong>La Sourate Al-Mulk</strong> (La Royauté) est le 67e chapitre du Coran, révélée à La Mecque, composée de 30 versets. Parmi toutes les sourates du Coran, elle occupe une place particulièrement honorée : le Prophète ﷺ ne s'endormait jamais sans l'avoir récitée, et l'a décrite comme une sourate qui intercède pour son compagnon dans la tombe. Comprendre ce que cette sourate dit — et à quoi elle nous invite à réfléchir — est la première étape pour en faire une partie vivante du culte quotidien."
            },
            {
              "t": "h2",
              "text": "La déclaration d'ouverture : toute la royauté appartient à Allah"
            },
            {
              "t": "quran",
              "text": "تَبَارَكَ الَّذِي بِيَدِهِ الْمُلْكُ وَهُوَ عَلَى كُلِّ شَيْءٍ قَدِيرٌ ۝ الَّذِي خَلَقَ الْمَوْتَ وَالْحَيَاةَ لِيَبْلُوَكُمْ أَيُّكُمْ أَحْسَنُ عَمَلًا ۚ وَهُوَ الْعَزِيزُ الْغَفُورُ",
              "ref": "Sourate Al-Mulk, 67:1–2"
            },
            {
              "t": "p",
              "html": "« Béni soit Celui en la main Duquel est la royauté, et Il est sur toute chose Omnipotent — Celui qui a créé la mort et la vie pour vous éprouver et voir qui d'entre vous est le meilleur en œuvre. Et Il est le Puissant, le Pardonneur. » La sourate s'ouvre non pas sur un rite, mais en ancrant le croyant dans une vérité cosmique : <em>tout pouvoir appartient à Allah seul</em>. Le mot arabe <em>tabarak</em> — dont la sourate tire son surnom bien-aimé <strong>Al-Tabarak</strong> — décrit une source de bénédiction perpétuelle et débordante. Revenir chaque nuit à cette déclaration recentre le cœur."
            },
            {
              "t": "h2",
              "text": "Le hadith : une sourate de trente versets qui intercède"
            },
            {
              "t": "p",
              "html": "Abu Hurayra (ra) a rapporté que le Prophète ﷺ a dit : <em>« Il y a dans le Coran une sourate de trente versets qui intercédera pour un homme jusqu'à ce qu'il soit pardonné — c'est : Tabarak alladhi biyadihi al-mulk. »</em> (Abu Dawud 1400 ; Tirmidhi 2891, classé hasan ; Ibn Majah 3786) Les savants expliquent que cette intercession est spécifiquement destinée à protéger son récitant du châtiment de la tombe. Les premiers savants lui ont donc attribué les titres <strong>Al-Mani'ah</strong> (celle qui prévient le châtiment) et <strong>Al-Waqiyah</strong> (le bouclier protecteur)."
            },
            {
              "t": "h2",
              "text": "La sunna nocturne du Prophète ﷺ"
            },
            {
              "t": "p",
              "html": "Jabir ibn Abdullah (ra) a rapporté que le Prophète ﷺ ne s'endormait pas avant d'avoir récité la Sourate As-Sajdah (32) et la Sourate Al-Mulk (67). (Tirmidhi 2892, hasan) Cela a établi une pratique nocturne préservée par les Compagnons et leurs successeurs. De nombreux savants recommandent d'associer la récitation à une routine vespérale plus large ; pour l'étiquette prophétique complète du sommeil, voir notre guide sur la <a href='sunna-du-sommeil.html'>sunna du sommeil</a>."
            },
            {
              "t": "h2",
              "text": "Thèmes clés de la Sourate Al-Mulk"
            },
            {
              "t": "cards",
              "cards": [
                {
                  "icon": "🌌",
                  "title": "La souveraineté absolue d'Allah",
                  "text": "Toute la royauté et tout le pouvoir appartiennent à Allah seul. Revenir chaque nuit à cette vérité forge un cœur en paix, quelle que soit l'agitation du monde."
                },
                {
                  "icon": "⚖️",
                  "title": "La vie et la mort comme épreuve",
                  "text": "Le verset 2 révèle que la mort et la vie ont été créées pour éprouver lequel d'entre nous est le meilleur en œuvre — non le plus nombreux. La sincérité et la qualité comptent plus que la quantité."
                },
                {
                  "icon": "🔭",
                  "title": "Les cieux : cherche une fissure",
                  "text": "Les versets 3–5 décrivent les sept cieux en couches parfaites, ornés d'étoiles, sans fissure ni défaut. Allah nous invite à regarder — et à n'en trouver aucune."
                },
                {
                  "icon": "💧",
                  "title": "La provision vient d'Allah seul",
                  "text": "La sourate se clôt en demandant : si l'eau sous la terre disparaissait, qui pourrait faire jaillir de l'eau courante ? Allah seul — un appel à la dépendance totale envers Lui."
                }
              ]
            },
            {
              "t": "h2",
              "text": "Un verset à emporter"
            },
            {
              "t": "quran",
              "text": "أَلَا يَعْلَمُ مَنْ خَلَقَ وَهُوَ اللَّطِيفُ الْخَبِيرُ",
              "ref": "Sourate Al-Mulk, 67:14"
            },
            {
              "t": "p",
              "html": "« Celui qui a créé ne saurait-Il pas — alors qu'Il est le Subtil, le Parfaitement Informé ? » Ce verset est l'une des réponses les plus puissantes du Coran à l'inquiétude face à l'invisible. Allah t'a créé avec une connaissance parfaite de ta nature, de ta situation et de tes besoins. Associé au message d'ouverture de la souveraineté, le verset 67:14 offre au croyant un cadre complet : <em>Allah maîtrise tout et te connaît parfaitement</em>."
            },
            {
              "t": "h2",
              "text": "Construire l'habitude nocturne"
            },
            {
              "t": "p",
              "html": "Le moyen le plus sûr de ne jamais manquer la Sourate Al-Mulk est de l'attacher à une habitude existante : après la prière d'Isha, ou lorsque tu éteins la lumière. Commence par quelques versets à la fois, en lisant avec la traduction pour en absorber le sens, et progresse graduellement vers la récitation des 30 versets de mémoire. La <a href='vertu-apprendre-enseigner-coran.html'>vertu d'apprendre et d'enseigner le Coran</a> est immense, et à 30 versets cette sourate est un excellent point de départ."
            }
          ],
          "cta": {
            "title": "Récitez la Sourate Al-Mulk chaque nuit avec DeenPal",
            "text": "Obtenez le texte arabe complet de la Sourate Al-Mulk avec translittération, audio et traduction — plus un rappel nocturne — dans une seule application gratuite.",
            "btn": "Télécharger DeenPal gratuitement"
          },
          "footer_nav": {
            "prev": {
              "href": "sourate-al-ikhlas-signification-vertus.html",
              "title": "Sourate Al-Ikhlas : signification et vertus"
            },
            "related": {
              "href": "sourate-ya-sin-signification-vertus.html",
              "title": "Sourate Ya-Sin : signification, vertus et quand la réciter"
            }
          },
          "faq": [
            {
              "q": "Quel est le principal bienfait de réciter la Sourate Al-Mulk chaque nuit ?",
              "a": "Le Prophète ﷺ a dit qu'une sourate de 30 versets — la Sourate Al-Mulk — intercédera pour son récitant jusqu'à ce qu'il soit pardonné, et les savants relient cela spécifiquement à la protection contre le châtiment de la tombe. (Abu Dawud, Tirmidhi, Ibn Majah)"
            },
            {
              "q": "Quels sont les autres noms de la Sourate Al-Mulk ?",
              "a": "La Sourate Al-Mulk est aussi connue sous les noms d'Al-Tabarak (d'après son mot d'ouverture), Al-Mani'ah (celle qui prévient le châtiment) et Al-Waqiyah (le bouclier protecteur)."
            },
            {
              "q": "Le Prophète ﷺ récitait-il vraiment la Sourate Al-Mulk chaque nuit ?",
              "a": "Oui. Jabir ibn Abdullah (ra) a rapporté que le Prophète ﷺ ne s'endormait pas avant d'avoir récité la Sourate As-Sajdah et la Sourate Al-Mulk. Cela est rapporté chez Tirmidhi et classé hasan."
            },
            {
              "q": "Combien de versets comporte la Sourate Al-Mulk et combien de temps prend la récitation ?",
              "a": "La Sourate Al-Mulk comporte 30 versets. À un rythme mesuré, la récitation prend environ quatre à six minutes."
            },
            {
              "q": "Quel est le thème central de la Sourate Al-Mulk ?",
              "a": "La sourate établit la souveraineté absolue d'Allah, explique que la vie et la mort sont une épreuve pour voir qui accomplit les meilleures œuvres, et nous rappelle que toute provision et tout pouvoir appartiennent à Allah seul."
            },
            {
              "q": "Quel est le meilleur moment pour réciter la Sourate Al-Mulk ?",
              "a": "La pratique prophétique était de la réciter la nuit avant de dormir. De nombreux musulmans la récitent après la prière d'Isha ou juste avant de se coucher."
            }
          ]
        }
      }
    },
    {
      "img_class": "blog-card__img--2",
      "langs": {
        "en": {
          "slug": "istikhara-dua-meaning-and-how-to-use",
          "title": "The Istikhara Dua: Full Arabic Text, Meaning and How to Use It",
          "meta_desc": "The complete Arabic text of the istikhara dua with transliteration and translation, a breakdown of each phrase, when to recite it, and answers to the most common questions.",
          "og_title": "The Istikhara Dua: Full Text, Meaning and When to Recite It",
          "og_desc": "What you are actually saying in the istikhara dua, phrase by phrase — with the full Arabic text, transliteration, and clear answers to common questions.",
          "category": "Dua",
          "h1": "The Istikhara Dua: Full Arabic Text, Meaning and How to Use It",
          "read_label": "8 min read",
          "excerpt": "The istikhara dua is one of the most powerful supplications in Islam. This guide presents the full Arabic text with transliteration, unpacks what each phrase means, and explains exactly when and how to recite it.",
          "sections": [
            {
              "t": "p",
              "html": "The <strong>istikhara dua</strong> is one of the most complete acts of tawakkul (trust in Allah) that a Muslim can perform. Unlike many supplications, it does not ask for a specific outcome — it asks Allah to <em>choose</em> and to <em>make the choice easy</em>. Jabir ibn Abdullah (RA) narrated that the Prophet ﷺ used to teach the Companions this dua for all their affairs, just as he would teach them a surah of the Quran, saying: <em>\"When any one of you intends a matter, let him pray two rak'ahs of non-obligatory prayer, then say…\"</em> (Bukhari 6382) This guide focuses specifically on the dua itself: its full text, the meaning of each phrase, and how to use it correctly. For the full prayer ritual, see our guide to <a href='salatul-istikhara-guide.html'>how to pray Salatul Istikhara</a>."
            },
            {
              "t": "h2",
              "text": "The Complete Istikhara Dua"
            },
            {
              "t": "highlight",
              "arabic": "اللَّهُمَّ إِنِّي أَسْتَخِيرُكَ بِعِلْمِكَ وَأَسْتَقْدِرُكَ بِقُدْرَتِكَ وَأَسْأَلُكَ مِنْ فَضْلِكَ الْعَظِيمِ فَإِنَّكَ تَقْدِرُ وَلَا أَقْدِرُ وَتَعْلَمُ وَلَا أَعْلَمُ وَأَنْتَ عَلَّامُ الْغُيُوبِ اللَّهُمَّ إِنْ كُنْتَ تَعْلَمُ أَنَّ هَذَا الْأَمْرَ خَيْرٌ لِي فِي دِينِي وَمَعَاشِي وَعَاقِبَةِ أَمْرِي فَاقْدُرْهُ لِي وَيَسِّرْهُ لِي ثُمَّ بَارِكْ لِي فِيهِ وَإِنْ كُنْتَ تَعْلَمُ أَنَّ هَذَا الْأَمْرَ شَرٌّ لِي فِي دِينِي وَمَعَاشِي وَعَاقِبَةِ أَمْرِي فَاصْرِفْهُ عَنِّي وَاصْرِفْنِي عَنْهُ وَاقْدُرْ لِي الْخَيْرَ حَيْثُ كَانَ ثُمَّ أَرْضِنِي بِهِ",
              "trans": "Allahumma inni astakhiruka bi-'ilmika wa-astaqdiruka bi-qudratika wa-as'aluka min fadlikal-'azim. Fa-innaka taqdiru wa-la aqdiru wa-ta'lamu wa-la a'lamu wa-anta 'allamu al-ghuyub. Allahumma in kunta ta'lamu anna hadhal-amra khayrun li fi dini wa-ma'ashi wa-'aqibati amri, faqdurhu li wa-yassirhu li thumma barik li fihi. Wa-in kunta ta'lamu anna hadhal-amra sharrun li fi dini wa-ma'ashi wa-'aqibati amri, fasrifhu 'anni wa-srifni 'anhu, wa-qdur liyal-khayra haythu kana thumma ardini bihi.",
              "note": "The complete istikhara dua as taught by the Prophet ﷺ to his Companions. (Bukhari 6382)"
            },
            {
              "t": "h2",
              "text": "Translation"
            },
            {
              "t": "p",
              "html": "<em>\"O Allah, I seek goodness from You through Your knowledge, and I seek ability from You through Your power, and I ask You of Your great bounty. For You are able and I am not, and You know and I do not know, and You are the Knower of all that is hidden. O Allah, if You know that this matter is good for me in my religion, my livelihood and the outcome of my affairs — then decree it for me, make it easy for me, and bless me in it. And if You know that this matter is harmful to me in my religion, my livelihood and the outcome of my affairs — then turn it away from me and turn me away from it, and decree good for me wherever it may be, then make me content with it.\"</em>"
            },
            {
              "t": "h2",
              "text": "Understanding Each Part of the Dua"
            },
            {
              "t": "ul",
              "items": [
                "<strong>Astakhiruka bi-'ilmika</strong> — \"I seek goodness from You through Your knowledge.\" You are acknowledging that Allah's knowledge is infinite while yours is limited. The choice is being referred upward.",
                "<strong>Astaqdiruka bi-qudratika</strong> — \"I seek ability from You through Your power.\" Not only does Allah know what is best, He has the power to bring it about and make it easy.",
                "<strong>As'aluka min fadlikal-'azim</strong> — \"I ask You of Your great bounty.\" Whatever the outcome, you are asking from Allah's generosity — not just for the matter itself, but for the good that surrounds it.",
                "<strong>Hadhal-amr</strong> — \"This matter.\" At this point in the dua, you think of or name the specific decision you are making. The dua text does not change; you simply hold that matter in your mind.",
                "<strong>Fi dini wa-ma'ashi wa-'aqibati amri</strong> — \"In my religion, my livelihood, and the outcome of my affairs.\" You are asking Allah to judge the matter across three dimensions: your faith, your daily life, and your long-term future.",
                "<strong>Ardini bihi</strong> — \"Make me content with it.\" The closing phrase is perhaps the most important: you are asking Allah to grant you inner peace with whatever He decrees, not just the result itself."
              ]
            },
            {
              "t": "h2",
              "text": "When and How to Recite the Dua"
            },
            {
              "t": "p",
              "html": "The established sunnah is to recite the istikhara dua <strong>after the salam</strong> (the concluding salutation) of two voluntary rak'ahs, while raising your hands in supplication. The dua is not recited during the prayer itself. Many scholars recommend reciting it immediately after the prayer ends, before you are distracted by other thoughts. For a practical step-by-step of the prayer itself, see our <a href='salatul-istikhara-guide.html'>guide to Salatul Istikhara</a>."
            },
            {
              "t": "h2",
              "text": "Common Questions About the Dua"
            },
            {
              "t": "cards",
              "cards": [
                {
                  "icon": "🗣️",
                  "title": "Do I say 'hadha al-amr' out loud?",
                  "text": "The phrase 'hadha al-amr' (this matter) stays in the dua text as-is. At that point, you think of your specific matter in your heart. You do not replace the Arabic words — you simply hold the intention in mind."
                },
                {
                  "icon": "🌍",
                  "title": "Can I recite the dua in my own language?",
                  "text": "The established dua should be recited in Arabic as the Prophet ﷺ taught it. You may add personal supplications in any language before or after, but the core dua is in Arabic."
                },
                {
                  "icon": "🔁",
                  "title": "Can I recite it multiple times?",
                  "text": "Yes. Many scholars permitted repeating the full istikhara — prayer and dua — up to seven times if clarity does not come. Each repetition is a renewed act of turning to Allah."
                },
                {
                  "icon": "🤲",
                  "title": "What is the adab of making the dua?",
                  "text": "Face the qiblah if possible, raise your hands, and recite with full presence of heart. For principles that apply to all supplications, see our guide to the <a href='adab-of-making-dua.html'>adab of making dua</a>."
                }
              ]
            },
            {
              "t": "p",
              "html": "The closing words — <em>\"make me content with it\"</em> — are what distinguish the istikhara dua from ordinary petitions. You are not just asking for the good option; you are asking Allah to grant you acceptance and satisfaction with whatever He wills. This is why scholars consider istikhara one of the highest expressions of <strong>tawakkul</strong>: not resignation, but active trust in the One who knows what you cannot."
            }
          ],
          "cta": {
            "title": "Have the Istikhara Dua at Your Fingertips with DeenPal",
            "text": "Get the full istikhara dua with Arabic, transliteration and audio — alongside prayer times, reminders and adhkar — in one free app.",
            "btn": "Download DeenPal Free"
          },
          "footer_nav": {
            "prev": {
              "href": "salatul-istikhara-guide.html",
              "title": "Salatul Istikhara: How to Pray the Prayer of Guidance"
            },
            "related": {
              "href": "adab-of-making-dua.html",
              "title": "The Adab of Making Dua: How Supplications Get Answered"
            }
          },
          "faq": [
            {
              "q": "When exactly do I recite the istikhara dua?",
              "a": "The istikhara dua is recited after the salam (concluding salutation) of the two voluntary rak'ahs, not during the prayer. You raise your hands and recite it as a supplication immediately after finishing the prayer."
            },
            {
              "q": "Do I need to say 'hadha al-amr' in Arabic for my specific matter?",
              "a": "No. The phrase 'hadha al-amr' (this matter) remains in the dua text as it is. At that point you simply hold your specific matter in your heart or mind — the Arabic wording of the dua itself does not change."
            },
            {
              "q": "Can I recite the istikhara dua without praying two rak'ahs first?",
              "a": "The established sunnah is to recite the dua after the two rak'ahs of istikhara prayer. Scholars generally recommend following the full sunnah — prayer first, then the dua."
            },
            {
              "q": "What does 'fi dini wa ma'ashi wa aqibati amri' mean?",
              "a": "It means 'in my religion, my livelihood, and the outcome of my affairs.' You are asking Allah to assess whether this matter is beneficial across all three dimensions — your faith, your worldly life, and your long-term future."
            },
            {
              "q": "What does 'ardini bihi' mean at the end of the dua?",
              "a": "'Ardini bihi' means 'make me content with it' or 'grant me satisfaction with it.' This asks Allah not only for the good outcome but for inner peace and acceptance with whatever He decrees."
            },
            {
              "q": "How many times can I repeat the istikhara dua?",
              "a": "Many scholars permitted repeating the full istikhara — the two rak'ahs and the dua — up to seven times if the heart has not found clarity. Each repetition is a fresh act of turning to Allah for guidance."
            }
          ]
        },
        "nl": {
          "slug": "istikhara-dua-betekenis-en-gebruik",
          "title": "De Istikhara-Dua: Volledige Arabische Tekst, Betekenis en Gebruik",
          "meta_desc": "De volledige Arabische tekst van de istikhara-dua met transliteratie en vertaling, uitleg van elke zin, wanneer je hem reciteert, en antwoorden op de meestgestelde vragen.",
          "og_title": "De Istikhara-Dua: Volledige Tekst, Betekenis en Gebruik",
          "og_desc": "Wat je precies zegt in de istikhara-dua, zin voor zin — met volledige Arabische tekst, transliteratie en duidelijke antwoorden op veelgestelde vragen.",
          "category": "Dua",
          "h1": "De Istikhara-Dua: Volledige Arabische Tekst, Betekenis en Gebruik",
          "read_label": "8 min lezen",
          "excerpt": "De istikhara-dua is een van de krachtigste smeekbeden in de Islam. Deze gids presenteert de volledige Arabische tekst met transliteratie, legt elke zin uit en verklaart wanneer en hoe je hem reciteert.",
          "sections": [
            {
              "t": "p",
              "html": "De <strong>istikhara-dua</strong> is een van de meest volledige uitdrukkingen van tawakkul (vertrouwen op Allah) die een moslim kan verrichten. In tegenstelling tot veel smeekbeden vraagt zij niet om een specifieke uitkomst — zij vraagt Allah om <em>te kiezen</em> en om de keuze gemakkelijk te maken. Jabir ibn Abdullah (ra) overleverde dat de Profeet ﷺ de metgezellen deze dua voor al hun zaken leerde, net zoals hij hun een soera van de Koran leerde. (Boechari 6382) Deze gids richt zich specifiek op de dua zelf: de volledige tekst, de betekenis van elke zin en hoe je hem correct gebruikt. Voor het volledige gebedsritueel, zie onze gids over <a href='salatul-istikhara-gids.html'>Salatul Istikhara bidden</a>."
            },
            {
              "t": "h2",
              "text": "De Volledige Istikhara-Dua"
            },
            {
              "t": "highlight",
              "arabic": "اللَّهُمَّ إِنِّي أَسْتَخِيرُكَ بِعِلْمِكَ وَأَسْتَقْدِرُكَ بِقُدْرَتِكَ وَأَسْأَلُكَ مِنْ فَضْلِكَ الْعَظِيمِ فَإِنَّكَ تَقْدِرُ وَلَا أَقْدِرُ وَتَعْلَمُ وَلَا أَعْلَمُ وَأَنْتَ عَلَّامُ الْغُيُوبِ اللَّهُمَّ إِنْ كُنْتَ تَعْلَمُ أَنَّ هَذَا الْأَمْرَ خَيْرٌ لِي فِي دِينِي وَمَعَاشِي وَعَاقِبَةِ أَمْرِي فَاقْدُرْهُ لِي وَيَسِّرْهُ لِي ثُمَّ بَارِكْ لِي فِيهِ وَإِنْ كُنْتَ تَعْلَمُ أَنَّ هَذَا الْأَمْرَ شَرٌّ لِي فِي دِينِي وَمَعَاشِي وَعَاقِبَةِ أَمْرِي فَاصْرِفْهُ عَنِّي وَاصْرِفْنِي عَنْهُ وَاقْدُرْ لِي الْخَيْرَ حَيْثُ كَانَ ثُمَّ أَرْضِنِي بِهِ",
              "trans": "Allahumma inni astakhiruka bi-'ilmika wa-astaqdiruka bi-qudratika wa-as'aluka min fadlikal-'azim. Fa-innaka taqdiru wa-la aqdiru wa-ta'lamu wa-la a'lamu wa-anta 'allamu al-ghuyub. Allahumma in kunta ta'lamu anna hadhal-amra khayrun li fi dini wa-ma'ashi wa-'aqibati amri, faqdurhu li wa-yassirhu li thumma barik li fihi. Wa-in kunta ta'lamu anna hadhal-amra sharrun li fi dini wa-ma'ashi wa-'aqibati amri, fasrifhu 'anni wa-srifni 'anhu, wa-qdur liyal-khayra haythu kana thumma ardini bihi.",
              "note": "De volledige istikhara-dua zoals geleerd door de Profeet ﷺ aan zijn metgezellen. (Boechari 6382)"
            },
            {
              "t": "h2",
              "text": "Vertaling"
            },
            {
              "t": "p",
              "html": "<em>\"O Allah, ik zoek het goede bij U door Uw kennis, en ik zoek kracht bij U door Uw macht, en ik vraag U van Uw grote gunst. Want U bent in staat en ik niet, en U weet en ik weet niet, en U bent de Kenner van alles wat verborgen is. O Allah, als U weet dat deze zaak goed voor mij is in mijn religie, mijn levensonderhoud en de uitkomst van mijn zaken — beschik het dan voor mij, maak het gemakkelijk voor mij en zegen mij erin. En als U weet dat deze zaak schadelijk voor mij is in mijn religie, mijn levensonderhoud en de uitkomst van mijn zaken — wend het dan van mij af en wend mij ervan af, en beschik het goede voor mij waar het ook zij, en maak mij er vervolgens tevreden mee.\"</em>"
            },
            {
              "t": "h2",
              "text": "Elke Deel van de Dua Begrijpen"
            },
            {
              "t": "ul",
              "items": [
                "<strong>Astakhiruka bi-'ilmika</strong> — \"Ik zoek het goede bij U door Uw kennis.\" Je erkent dat Allah's kennis oneindig is terwijl de jouwe beperkt is. De keuze wordt aan Hem overgedragen.",
                "<strong>Astaqdiruka bi-qudratika</strong> — \"Ik zoek kracht bij U door Uw macht.\" Niet alleen weet Allah wat het beste is, Hij heeft ook de macht om het tot stand te brengen en gemakkelijk te maken.",
                "<strong>As'aluka min fadlikal-'azim</strong> — \"Ik vraag U van Uw grote gunst.\" Wat de uitkomst ook is, je vraagt vanuit Allah's vrijgevigheid.",
                "<strong>Hadhal-amr</strong> — \"Deze zaak.\" Op dit moment in de dua denk je aan of noem je de specifieke beslissing die je neemt. De tekst van de dua verandert niet; je houdt die zaak eenvoudig in gedachten.",
                "<strong>Fi dini wa-ma'ashi wa-'aqibati amri</strong> — \"In mijn religie, mijn levensonderhoud en de uitkomst van mijn zaken.\" Je vraagt Allah de zaak te beoordelen op drie dimensies: je geloof, je dagelijks leven en je toekomstige uitkomst.",
                "<strong>Ardini bihi</strong> — \"Maak mij er tevreden mee.\" De slotwoorden zijn wellicht de belangrijkste: je vraagt Allah innerlijke vrede te schenken met wat Hij ook beschikt."
              ]
            },
            {
              "t": "h2",
              "text": "Wanneer en Hoe Je de Dua Reciteert"
            },
            {
              "t": "p",
              "html": "De gevestigde soenna is de istikhara-dua te reciteren <strong>na de salam</strong> (de afsluitende groet) van twee vrijwillige rak'ah, terwijl je je handen opheft in smeekbede. De dua wordt niet tijdens het gebed zelf gereciteerd. Veel geleerden bevelen aan hem direct na het gebed te reciteren, voor je door andere gedachten wordt afgeleid. Zie voor een praktische stap-voor-stap van het gebed onze <a href='salatul-istikhara-gids.html'>gids voor Salatul Istikhara</a>."
            },
            {
              "t": "h2",
              "text": "Veelgestelde Vragen over de Dua"
            },
            {
              "t": "cards",
              "cards": [
                {
                  "icon": "🗣️",
                  "title": "Zeg ik 'hadha al-amr' hardop?",
                  "text": "De zin 'hadha al-amr' (deze zaak) blijft in de dua-tekst staan zoals hij is. Op dat moment denk je aan jouw specifieke zaak in je hart. Je vervangt de Arabische woorden niet — je houdt eenvoudig de intentie in gedachten."
                },
                {
                  "icon": "🌍",
                  "title": "Kan ik de dua in mijn eigen taal reciteren?",
                  "text": "De gevestigde dua moet in het Arabisch worden gereciteerd zoals de Profeet ﷺ het leerde. Je kunt voor of na persoonlijke smeekbeden in elke taal toevoegen, maar de kern-dua is in het Arabisch."
                },
                {
                  "icon": "🔁",
                  "title": "Kan ik hem meerdere keren reciteren?",
                  "text": "Ja. Veel geleerden stonden toe de volledige istikhara — gebed en dua — tot zeven keer te herhalen als er geen duidelijkheid komt. Elke herhaling is een vernieuwd wenden tot Allah."
                },
                {
                  "icon": "🤲",
                  "title": "Wat is de adab van het doen van de dua?",
                  "text": "Richt je indien mogelijk naar de qibla, hef je handen op en reciteer met volledige aanwezigheid van hart. Zie onze gids over de <a href='adab-van-dua-maken.html'>adab van het doen van dua</a>."
                }
              ]
            },
            {
              "t": "p",
              "html": "De slotwoorden — <em>\"maak mij er tevreden mee\"</em> — onderscheiden de istikhara-dua van gewone verzoeken. Je vraagt niet alleen om de goede optie; je vraagt Allah om innerlijke aanvaarding en tevredenheid met wat Hij ook beschikt. Dat is waarom geleerden istikhara beschouwen als een van de hoogste uitdrukkingen van <strong>tawakkul</strong>: niet berusting, maar actief vertrouwen in Degene die weet wat jij niet kunt weten."
            }
          ],
          "cta": {
            "title": "Heb de Istikhara-Dua bij de Hand met DeenPal",
            "text": "Krijg de volledige istikhara-dua met Arabisch, transliteratie en audio — samen met gebedstijden, herinneringen en adhkar — in één gratis app.",
            "btn": "Download DeenPal Gratis"
          },
          "footer_nav": {
            "prev": {
              "href": "salatul-istikhara-gids.html",
              "title": "Salatul Istikhara: Het Gebed om Leiding Bidden"
            },
            "related": {
              "href": "adab-van-dua-maken.html",
              "title": "De Adab van het Doen van Dua"
            }
          },
          "faq": [
            {
              "q": "Wanneer reciteer ik de istikhara-dua precies?",
              "a": "De istikhara-dua wordt gereciteerd na de salam (afsluitende groet) van de twee vrijwillige rak'ah, niet tijdens het gebed. Je heft je handen op en reciteert hem als smeekbede direct na het beëindigen van het gebed."
            },
            {
              "q": "Moet ik 'hadha al-amr' in het Arabisch zeggen voor mijn specifieke zaak?",
              "a": "Nee. De zin 'hadha al-amr' (deze zaak) blijft in de dua-tekst zoals hij is. Op dat moment houd je eenvoudig je specifieke zaak in je hart of gedachten — de Arabische bewoording van de dua verandert niet."
            },
            {
              "q": "Kan ik de istikhara-dua reciteren zonder eerst twee rak'ah te bidden?",
              "a": "De gevestigde soenna is de dua na de twee rak'ah istikhara-gebed te reciteren. Geleerden bevelen over het algemeen aan de volledige soenna te volgen — eerst het gebed, dan de dua."
            },
            {
              "q": "Wat betekent 'fi dini wa ma'ashi wa aqibati amri'?",
              "a": "Het betekent 'in mijn religie, mijn levensonderhoud en de uitkomst van mijn zaken.' Je vraagt Allah de zaak op drie dimensies te beoordelen — je geloof, je wereldse leven en je toekomstige uitkomst."
            },
            {
              "q": "Wat betekent 'ardini bihi' aan het einde van de dua?",
              "a": "'Ardini bihi' betekent 'maak mij er tevreden mee.' Dit vraagt Allah niet alleen om de goede uitkomst, maar ook om innerlijke vrede en aanvaarding met wat Hij ook beschikt."
            },
            {
              "q": "Hoe vaak kan ik de istikhara-dua herhalen?",
              "a": "Veel geleerden stonden toe de volledige istikhara — de twee rak'ah en de dua — tot zeven keer te herhalen als het hart geen duidelijkheid vindt. Elke herhaling is een nieuwe handeling van wenden tot Allah voor leiding."
            }
          ]
        },
        "de": {
          "slug": "istikhara-dua-bedeutung-und-anwendung",
          "title": "Das Istikhara-Bittgebet: Vollständiger arabischer Text, Bedeutung und Anwendung",
          "meta_desc": "Der vollständige arabische Text des Istikhara-Bittgebets mit Transliteration und Übersetzung, Erklärung jedes Satzteils, wann man es rezitiert und Antworten auf die häufigsten Fragen.",
          "og_title": "Das Istikhara-Bittgebet: Vollständiger Text, Bedeutung und Anwendung",
          "og_desc": "Was du Satz für Satz im Istikhara-Bittgebet sagst — mit vollständigem arabischen Text, Transliteration und klaren Antworten auf häufige Fragen.",
          "category": "Bittgebet",
          "h1": "Das Istikhara-Bittgebet: Vollständiger arabischer Text, Bedeutung und Anwendung",
          "read_label": "8 Min. Lesezeit",
          "excerpt": "Das Istikhara-Bittgebet ist eines der kraftvollsten Bittgebete im Islam. Dieser Leitfaden stellt den vollständigen arabischen Text mit Transliteration vor, erklärt jeden Satzteil und erläutert genau, wann und wie man es rezitiert.",
          "sections": [
            {
              "t": "p",
              "html": "Das <strong>Istikhara-Bittgebet</strong> ist einer der vollständigsten Ausdrücke von Tawakkul (Vertrauen auf Allah), den ein Muslim vollziehen kann. Anders als viele Bittgebete bittet es nicht um ein bestimmtes Ergebnis — es bittet Allah zu <em>wählen</em> und die Wahl zu erleichtern. Jabir ibn Abdullah (ra) überlieferte, dass der Prophet ﷺ den Gefährten dieses Bittgebet für alle ihre Angelegenheiten lehrte, so wie er ihnen eine Sure des Qurans lehrte. (Bukhari 6382) Dieser Leitfaden konzentriert sich speziell auf das Bittgebet selbst: seinen vollständigen Text, die Bedeutung jedes Satzteils und seine korrekte Anwendung. Für das vollständige Gebetsritual, siehe unsere Anleitung zum <a href='salatul-istikhara-anleitung.html'>Salatul Istikhara-Gebet</a>."
            },
            {
              "t": "h2",
              "text": "Das vollständige Istikhara-Bittgebet"
            },
            {
              "t": "highlight",
              "arabic": "اللَّهُمَّ إِنِّي أَسْتَخِيرُكَ بِعِلْمِكَ وَأَسْتَقْدِرُكَ بِقُدْرَتِكَ وَأَسْأَلُكَ مِنْ فَضْلِكَ الْعَظِيمِ فَإِنَّكَ تَقْدِرُ وَلَا أَقْدِرُ وَتَعْلَمُ وَلَا أَعْلَمُ وَأَنْتَ عَلَّامُ الْغُيُوبِ اللَّهُمَّ إِنْ كُنْتَ تَعْلَمُ أَنَّ هَذَا الْأَمْرَ خَيْرٌ لِي فِي دِينِي وَمَعَاشِي وَعَاقِبَةِ أَمْرِي فَاقْدُرْهُ لِي وَيَسِّرْهُ لِي ثُمَّ بَارِكْ لِي فِيهِ وَإِنْ كُنْتَ تَعْلَمُ أَنَّ هَذَا الْأَمْرَ شَرٌّ لِي فِي دِينِي وَمَعَاشِي وَعَاقِبَةِ أَمْرِي فَاصْرِفْهُ عَنِّي وَاصْرِفْنِي عَنْهُ وَاقْدُرْ لِي الْخَيْرَ حَيْثُ كَانَ ثُمَّ أَرْضِنِي بِهِ",
              "trans": "Allahumma inni astakhiruka bi-'ilmika wa-astaqdiruka bi-qudratika wa-as'aluka min fadlikal-'azim. Fa-innaka taqdiru wa-la aqdiru wa-ta'lamu wa-la a'lamu wa-anta 'allamu al-ghuyub. Allahumma in kunta ta'lamu anna hadhal-amra khayrun li fi dini wa-ma'ashi wa-'aqibati amri, faqdurhu li wa-yassirhu li thumma barik li fihi. Wa-in kunta ta'lamu anna hadhal-amra sharrun li fi dini wa-ma'ashi wa-'aqibati amri, fasrifhu 'anni wa-srifni 'anhu, wa-qdur liyal-khayra haythu kana thumma ardini bihi.",
              "note": "Das vollständige Istikhara-Bittgebet, wie es der Prophet ﷺ seinen Gefährten lehrte. (Bukhari 6382)"
            },
            {
              "t": "h2",
              "text": "Übersetzung"
            },
            {
              "t": "p",
              "html": "<em>„O Allah, ich suche das Gute bei Dir durch Dein Wissen, und ich suche Kraft bei Dir durch Deine Macht, und ich bitte Dich um Deine große Gunst. Denn Du bist fähig und ich nicht, und Du weißt und ich weiß nicht, und Du bist der Kenner alles Verborgenen. O Allah, wenn Du weißt, dass diese Angelegenheit gut für mich ist in meiner Religion, meinem Lebensunterhalt und dem Ausgang meiner Sache — dann bestimme sie für mich, mache sie mir leicht und segne mich darin. Und wenn Du weißt, dass diese Angelegenheit schädlich für mich ist in meiner Religion, meinem Lebensunterhalt und dem Ausgang meiner Sache — dann wende sie von mir ab und wende mich von ihr ab, und bestimme das Gute für mich, wo immer es sei, und mache mich dann damit zufrieden.\"</em>"
            },
            {
              "t": "h2",
              "text": "Jeden Teil des Bittgebets verstehen"
            },
            {
              "t": "ul",
              "items": [
                "<strong>Astakhiruka bi-'ilmika</strong> — „Ich suche das Gute bei Dir durch Dein Wissen.\" Du erkennst an, dass Allahs Wissen unendlich ist, während deines begrenzt ist. Die Entscheidung wird nach oben verwiesen.",
                "<strong>Astaqdiruka bi-qudratika</strong> — „Ich suche Kraft bei Dir durch Deine Macht.\" Allah weiß nicht nur, was das Beste ist — Er hat auch die Macht, es zu verwirklichen und zu erleichtern.",
                "<strong>As'aluka min fadlikal-'azim</strong> — „Ich bitte Dich um Deine große Gunst.\" Was auch immer das Ergebnis ist, du bittest aus Allahs Großzügigkeit heraus.",
                "<strong>Hadhal-amr</strong> — „Diese Angelegenheit.\" An dieser Stelle im Bittgebet denkst du an deine spezifische Entscheidung. Der Text des Bittgebets ändert sich nicht — du hältst die Angelegenheit einfach im Sinn.",
                "<strong>Fi dini wa-ma'ashi wa-'aqibati amri</strong> — „In meiner Religion, meinem Lebensunterhalt und dem Ausgang meiner Sache.\" Du bittest Allah, die Angelegenheit in drei Dimensionen zu beurteilen: deinen Glauben, dein tägliches Leben und deinen langfristigen Ausgang.",
                "<strong>Ardini bihi</strong> — „Mache mich damit zufrieden.\" Die Schlussworte sind vielleicht die wichtigsten: Du bittest Allah um inneren Frieden mit dem, was Er auch immer beschließt."
              ]
            },
            {
              "t": "h2",
              "text": "Wann und wie man das Bittgebet rezitiert"
            },
            {
              "t": "p",
              "html": "Die etablierte Sunna ist, das Istikhara-Bittgebet <strong>nach dem Salam</strong> (der abschließenden Grußformel) von zwei freiwilligen Rak'ah zu rezitieren, während man die Hände zum Bittgebet erhebt. Das Bittgebet wird nicht während des Gebets selbst rezitiert. Viele Gelehrte empfehlen, es unmittelbar nach dem Gebet zu rezitieren, bevor man von anderen Gedanken abgelenkt wird. Für eine praktische Schritt-für-Schritt-Anleitung des Gebets, siehe unsere <a href='salatul-istikhara-anleitung.html'>Anleitung zu Salatul Istikhara</a>."
            },
            {
              "t": "h2",
              "text": "Häufige Fragen zum Bittgebet"
            },
            {
              "t": "cards",
              "cards": [
                {
                  "icon": "🗣️",
                  "title": "Sage ich 'hadha al-amr' laut?",
                  "text": "Die Formulierung 'hadha al-amr' (diese Angelegenheit) bleibt im Bittgebetstext, wie er ist. An diesem Punkt denkst du im Herzen an deine spezifische Angelegenheit. Du ersetzt die arabischen Wörter nicht — du hältst einfach die Absicht im Sinn."
                },
                {
                  "icon": "🌍",
                  "title": "Kann ich das Bittgebet in meiner Muttersprache rezitieren?",
                  "text": "Das etablierte Bittgebet sollte auf Arabisch rezitiert werden, so wie es der Prophet ﷺ lehrte. Du kannst davor oder danach persönliche Bittgebete in jeder Sprache hinzufügen, aber das Kernbittgebet ist auf Arabisch."
                },
                {
                  "icon": "🔁",
                  "title": "Kann ich es mehrfach rezitieren?",
                  "text": "Ja. Viele Gelehrte erlaubten, die vollständige Istikhara — Gebet und Bittgebet — bis zu sieben Mal zu wiederholen, wenn keine Klarheit kommt. Jede Wiederholung ist eine erneuerte Hinwendung zu Allah."
                },
                {
                  "icon": "🤲",
                  "title": "Was ist der Adab des Bittgebets?",
                  "text": "Wende dich wenn möglich der Qibla zu, erhebe die Hände und rezitiere mit voller Anwesenheit des Herzens. Für Grundsätze, die für alle Bittgebete gelten, siehe unsere Anleitung zum <a href='adab-des-bittgebets.html'>Adab des Bittgebets</a>."
                }
              ]
            },
            {
              "t": "p",
              "html": "Die Schlussworte — <em>„mache mich damit zufrieden\"</em> — unterscheiden das Istikhara-Bittgebet von gewöhnlichen Bitten. Du bittest nicht nur um die gute Möglichkeit; du bittest Allah um innere Annahme und Zufriedenheit mit dem, was Er auch immer beschließt. Deshalb betrachten Gelehrte die Istikhara als einen der höchsten Ausdrücke von <strong>Tawakkul</strong>: nicht Resignation, sondern aktives Vertrauen in Denjenigen, der weiß, was du nicht weißt."
            }
          ],
          "cta": {
            "title": "Habe das Istikhara-Bittgebet griffbereit mit DeenPal",
            "text": "Erhalte das vollständige Istikhara-Bittgebet mit Arabisch, Transliteration und Audio — zusammen mit Gebetszeiten, Erinnerungen und Adhkar — in einer kostenlosen App.",
            "btn": "DeenPal kostenlos laden"
          },
          "footer_nav": {
            "prev": {
              "href": "salatul-istikhara-anleitung.html",
              "title": "Salatul Istikhara: Das Gebet um Rechtleitung"
            },
            "related": {
              "href": "adab-des-bittgebets.html",
              "title": "Der Adab des Bittgebets"
            }
          },
          "faq": [
            {
              "q": "Wann genau rezitiere ich das Istikhara-Bittgebet?",
              "a": "Das Istikhara-Bittgebet wird nach dem Salam (der abschließenden Grußformel) der zwei freiwilligen Rak'ah rezitiert, nicht während des Gebets. Du hebst die Hände und rezitierst es unmittelbar nach dem Beenden des Gebets."
            },
            {
              "q": "Muss ich 'hadha al-amr' für meine spezifische Angelegenheit auf Arabisch sagen?",
              "a": "Nein. Die Formulierung 'hadha al-amr' (diese Angelegenheit) bleibt im Bittgebetstext, wie er ist. An diesem Punkt hältst du einfach deine spezifische Angelegenheit im Herzen oder Sinn — die arabische Formulierung des Bittgebets ändert sich nicht."
            },
            {
              "q": "Kann ich das Istikhara-Bittgebet rezitieren, ohne vorher zwei Rak'ah zu beten?",
              "a": "Die etablierte Sunna ist, das Bittgebet nach den zwei Rak'ah des Istikhara-Gebets zu rezitieren. Gelehrte empfehlen im Allgemeinen, der vollständigen Sunna zu folgen — erst das Gebet, dann das Bittgebet."
            },
            {
              "q": "Was bedeutet 'fi dini wa ma'ashi wa aqibati amri'?",
              "a": "Es bedeutet 'in meiner Religion, meinem Lebensunterhalt und dem Ausgang meiner Sache.' Du bittest Allah, die Angelegenheit in drei Dimensionen zu beurteilen — deinen Glauben, dein weltliches Leben und deinen langfristigen Ausgang."
            },
            {
              "q": "Was bedeutet 'ardini bihi' am Ende des Bittgebets?",
              "a": "'Ardini bihi' bedeutet 'mache mich damit zufrieden.' Dies bittet Allah nicht nur um das gute Ergebnis, sondern auch um inneren Frieden und Annahme mit dem, was Er auch immer beschließt."
            },
            {
              "q": "Wie oft kann ich das Istikhara-Bittgebet wiederholen?",
              "a": "Viele Gelehrte erlaubten, die vollständige Istikhara — die zwei Rak'ah und das Bittgebet — bis zu sieben Mal zu wiederholen, wenn das Herz keine Klarheit findet. Jede Wiederholung ist eine neue Handlung der Hinwendung zu Allah."
            }
          ]
        },
        "fr": {
          "slug": "dua-istikhara-signification-et-utilisation",
          "title": "L'invocation d'istikhara : texte arabe complet, signification et comment l'utiliser",
          "meta_desc": "Le texte arabe complet de l'invocation d'istikhara avec translittération et traduction, explication de chaque phrase, quand la réciter et réponses aux questions les plus fréquentes.",
          "og_title": "L'invocation d'istikhara : texte complet, signification et utilisation",
          "og_desc": "Ce que tu dis phrase par phrase dans l'invocation d'istikhara — avec le texte arabe complet, la translittération et des réponses claires aux questions fréquentes.",
          "category": "Invocation",
          "h1": "L'invocation d'istikhara : texte arabe complet, signification et comment l'utiliser",
          "read_label": "8 min de lecture",
          "excerpt": "L'invocation d'istikhara est l'une des supplications les plus puissantes de l'Islam. Ce guide présente le texte arabe complet avec translittération, explique chaque phrase et précise exactement quand et comment la réciter.",
          "sections": [
            {
              "t": "p",
              "html": "L'<strong>invocation d'istikhara</strong> est l'une des expressions les plus complètes de tawakkul (confiance en Allah) qu'un musulman puisse accomplir. Contrairement à bien des supplications, elle ne demande pas un résultat précis — elle demande à Allah de <em>choisir</em> et de <em>faciliter ce choix</em>. Jabir ibn Abdullah (ra) a rapporté que le Prophète ﷺ enseignait cette invocation à ses Compagnons pour toutes leurs affaires, tout comme il leur enseignait une sourate du Coran. (Bukhari 6382) Ce guide se concentre spécifiquement sur l'invocation elle-même : son texte complet, la signification de chaque phrase et comment l'utiliser correctement. Pour le rituel de prière complet, voir notre guide pour <a href='priere-istikhara-guide.html'>prier Salat al-Istikhara</a>."
            },
            {
              "t": "h2",
              "text": "L'invocation d'istikhara complète"
            },
            {
              "t": "highlight",
              "arabic": "اللَّهُمَّ إِنِّي أَسْتَخِيرُكَ بِعِلْمِكَ وَأَسْتَقْدِرُكَ بِقُدْرَتِكَ وَأَسْأَلُكَ مِنْ فَضْلِكَ الْعَظِيمِ فَإِنَّكَ تَقْدِرُ وَلَا أَقْدِرُ وَتَعْلَمُ وَلَا أَعْلَمُ وَأَنْتَ عَلَّامُ الْغُيُوبِ اللَّهُمَّ إِنْ كُنْتَ تَعْلَمُ أَنَّ هَذَا الْأَمْرَ خَيْرٌ لِي فِي دِينِي وَمَعَاشِي وَعَاقِبَةِ أَمْرِي فَاقْدُرْهُ لِي وَيَسِّرْهُ لِي ثُمَّ بَارِكْ لِي فِيهِ وَإِنْ كُنْتَ تَعْلَمُ أَنَّ هَذَا الْأَمْرَ شَرٌّ لِي فِي دِينِي وَمَعَاشِي وَعَاقِبَةِ أَمْرِي فَاصْرِفْهُ عَنِّي وَاصْرِفْنِي عَنْهُ وَاقْدُرْ لِي الْخَيْرَ حَيْثُ كَانَ ثُمَّ أَرْضِنِي بِهِ",
              "trans": "Allahumma inni astakhiruka bi-'ilmika wa-astaqdiruka bi-qudratika wa-as'aluka min fadlikal-'azim. Fa-innaka taqdiru wa-la aqdiru wa-ta'lamu wa-la a'lamu wa-anta 'allamu al-ghuyub. Allahumma in kunta ta'lamu anna hadhal-amra khayrun li fi dini wa-ma'ashi wa-'aqibati amri, faqdurhu li wa-yassirhu li thumma barik li fihi. Wa-in kunta ta'lamu anna hadhal-amra sharrun li fi dini wa-ma'ashi wa-'aqibati amri, fasrifhu 'anni wa-srifni 'anhu, wa-qdur liyal-khayra haythu kana thumma ardini bihi.",
              "note": "L'invocation d'istikhara complète telle qu'enseignée par le Prophète ﷺ à ses Compagnons. (Bukhari 6382)"
            },
            {
              "t": "h2",
              "text": "Traduction"
            },
            {
              "t": "p",
              "html": "<em>« Ô Allah, je cherche le bien auprès de Toi par Ta science, je cherche la capacité auprès de Toi par Ta puissance, et je Te demande de Ta grande grâce. Car Tu peux et je ne peux pas, Tu sais et je ne sais pas, et Tu es le Connaisseur de tout ce qui est caché. Ô Allah, si Tu sais que cette affaire m'est bonne dans ma religion, ma subsistance et l'issue de mes affaires — décrète-la pour moi, facilite-la-moi et bénis-la-moi. Et si Tu sais que cette affaire m'est nuisible dans ma religion, ma subsistance et l'issue de mes affaires — détourne-la de moi et détourne-moi d'elle, et décrète le bien pour moi où qu'il se trouve, puis rends-moi satisfait de lui. »</em>"
            },
            {
              "t": "h2",
              "text": "Comprendre chaque partie de l'invocation"
            },
            {
              "t": "ul",
              "items": [
                "<strong>Astakhiruka bi-'ilmika</strong> — « Je cherche le bien auprès de Toi par Ta science. » Tu reconnais que la science d'Allah est infinie tandis que la tienne est limitée. La décision est renvoyée vers le Haut.",
                "<strong>Astaqdiruka bi-qudratika</strong> — « Je cherche la capacité auprès de Toi par Ta puissance. » Allah non seulement sait ce qui est le mieux, Il a aussi le pouvoir de le faire advenir et de le faciliter.",
                "<strong>As'aluka min fadlikal-'azim</strong> — « Je Te demande de Ta grande grâce. » Quel que soit le résultat, tu demandes depuis la générosité d'Allah.",
                "<strong>Hadhal-amr</strong> — « Cette affaire. » À ce moment de l'invocation, tu penses à ou nommes la décision spécifique que tu prends. Le texte de l'invocation ne change pas — tu gardes simplement cette affaire à l'esprit.",
                "<strong>Fi dini wa-ma'ashi wa-'aqibati amri</strong> — « Dans ma religion, ma subsistance et l'issue de mes affaires. » Tu demandes à Allah de juger l'affaire selon trois dimensions : ta foi, ta vie quotidienne et ton avenir à long terme.",
                "<strong>Ardini bihi</strong> — « Rends-moi satisfait de lui. » Les mots de clôture sont peut-être les plus importants : tu demandes à Allah de t'accorder la paix intérieure avec ce qu'Il décide, pas seulement le bon résultat lui-même."
              ]
            },
            {
              "t": "h2",
              "text": "Quand et comment réciter l'invocation"
            },
            {
              "t": "p",
              "html": "La sunna établie est de réciter l'invocation d'istikhara <strong>après le salam</strong> (la salutation conclusive) des deux rak'ahs surérogatoires, en levant les mains en supplication. L'invocation n'est pas récitée pendant la prière elle-même. De nombreux savants recommandent de la réciter immédiatement après la fin de la prière, avant d'être distrait par d'autres pensées. Pour une démarche pratique étape par étape de la prière, voir notre <a href='priere-istikhara-guide.html'>guide de la Salat al-Istikhara</a>."
            },
            {
              "t": "h2",
              "text": "Questions fréquentes sur l'invocation"
            },
            {
              "t": "cards",
              "cards": [
                {
                  "icon": "🗣️",
                  "title": "Est-ce que je dis 'hadha al-amr' à voix haute ?",
                  "text": "La formule 'hadha al-amr' (cette affaire) reste dans le texte de l'invocation tel quel. À ce moment, tu penses à ton affaire spécifique dans ton cœur. Tu ne remplaces pas les mots arabes — tu gardes simplement l'intention à l'esprit."
                },
                {
                  "icon": "🌍",
                  "title": "Puis-je réciter l'invocation dans ma propre langue ?",
                  "text": "L'invocation établie doit être récitée en arabe telle que le Prophète ﷺ l'a enseignée. Tu peux ajouter des supplications personnelles dans n'importe quelle langue avant ou après, mais l'invocation centrale est en arabe."
                },
                {
                  "icon": "🔁",
                  "title": "Puis-je la réciter plusieurs fois ?",
                  "text": "Oui. De nombreux savants ont permis de répéter l'istikhara complète — prière et invocation — jusqu'à sept fois si la clarté ne vient pas. Chaque répétition est un acte renouvelé de retour vers Allah."
                },
                {
                  "icon": "🤲",
                  "title": "Quel est l'adab de l'invocation ?",
                  "text": "Fais face à la qibla si possible, lève les mains et récite avec pleine présence du cœur. Pour les principes s'appliquant à toutes les supplications, voir notre guide sur l'<a href='adab-de-la-dua.html'>adab de la dua</a>."
                }
              ]
            },
            {
              "t": "p",
              "html": "Les mots de clôture — <em>« rends-moi satisfait de lui »</em> — distinguent l'invocation d'istikhara des pétitions ordinaires. Tu ne demandes pas seulement la bonne option ; tu demandes à Allah de t'accorder l'acceptation et la satisfaction intérieures, quelle que soit Sa décision. C'est pourquoi les savants considèrent l'istikhara comme l'une des plus hautes expressions du <strong>tawakkul</strong> : non pas la résignation, mais une confiance active en Celui qui sait ce que tu ne peux pas savoir."
            }
          ],
          "cta": {
            "title": "Ayez l'invocation d'istikhara à portée de main avec DeenPal",
            "text": "Obtenez l'invocation d'istikhara complète avec l'arabe, la translittération et l'audio — ainsi que les horaires de prière, des rappels et les adhkar — dans une seule application gratuite.",
            "btn": "Télécharger DeenPal gratuitement"
          },
          "footer_nav": {
            "prev": {
              "href": "priere-istikhara-guide.html",
              "title": "Salat al-Istikhara : prier la prière de guidance"
            },
            "related": {
              "href": "adab-de-la-dua.html",
              "title": "L'adab de la dua : comment les supplications sont exaucées"
            }
          },
          "faq": [
            {
              "q": "Quand exactement récite-t-on l'invocation d'istikhara ?",
              "a": "L'invocation d'istikhara est récitée après le salam (la salutation conclusive) des deux rak'ahs surérogatoires, pas pendant la prière. Tu lèves les mains et la récites comme supplication immédiatement après avoir terminé la prière."
            },
            {
              "q": "Dois-je dire 'hadha al-amr' en arabe pour mon affaire spécifique ?",
              "a": "Non. La formule 'hadha al-amr' (cette affaire) reste dans le texte de l'invocation tel quel. À ce moment, tu gardes simplement ton affaire spécifique dans ton cœur ou à l'esprit — la formulation arabe de l'invocation ne change pas."
            },
            {
              "q": "Puis-je réciter l'invocation d'istikhara sans prier deux rak'ahs au préalable ?",
              "a": "La sunna établie est de réciter l'invocation après les deux rak'ahs de la prière d'istikhara. Les savants recommandent généralement de suivre la sunna complète — d'abord la prière, puis l'invocation."
            },
            {
              "q": "Que signifie 'fi dini wa ma'ashi wa aqibati amri' ?",
              "a": "Cela signifie 'dans ma religion, ma subsistance et l'issue de mes affaires.' Tu demandes à Allah de juger l'affaire selon trois dimensions — ta foi, ta vie mondaine et ton avenir à long terme."
            },
            {
              "q": "Que signifie 'ardini bihi' à la fin de l'invocation ?",
              "a": "'Ardini bihi' signifie 'rends-moi satisfait de lui.' Cela demande à Allah non seulement le bon résultat, mais aussi la paix intérieure et l'acceptation de ce qu'Il décrète."
            },
            {
              "q": "Combien de fois puis-je répéter l'invocation d'istikhara ?",
              "a": "De nombreux savants ont permis de répéter l'istikhara complète — les deux rak'ahs et l'invocation — jusqu'à sept fois si le cœur ne trouve pas la clarté. Chaque répétition est un nouvel acte de retour vers Allah pour chercher Sa guidance."
            }
          ]
        }
      }
    }
  ]
}
